stsci_image-2.3.11.dist-info/RECORD
stsci_image-2.3.11.dist-info/WHEEL
stsci_image-2.3.11.dist-info/top_level.txt
stsci_image-2.3.11.dist-info/METADATA
stsci_image-2.3.11.dist-info/licenses/LICENSE.txt
stsci/image/_combine.cpython-313-darwin.so
stsci/image/version.py
stsci/image/combine.py
stsci/image/__init__.py
stsci/image/_image.py
stsci/image/numcombine.py
stsci/image/test/test_median.py
stsci/image/test/test_threshold.py
stsci/image/test/__init__.py
stsci/image/test/test_minimum.py
stsci/image/test/test_average.py
