Metadata-Version: 2.4
Name: stsci.image
Version: 2.3.11
Summary: Image array manipulation functions
Author-email: STScI <help@stsci.edu>
Project-URL: repository, https://github.com/spacetelescope/stsci.image
Classifier: Intended Audience :: Science/Research
Classifier: Operating System :: OS Independent
Classifier: Programming Language :: Python
Classifier: Topic :: Scientific/Engineering :: Astronomy
Classifier: Topic :: Software Development :: Libraries :: Python Modules
Requires-Python: >=3.9
License-File: LICENSE.txt
Requires-Dist: numpy
Requires-Dist: scipy
Provides-Extra: test
Requires-Dist: pytest; extra == "test"
Provides-Extra: docs
Requires-Dist: numpydoc; extra == "docs"
Requires-Dist: sphinx; extra == "docs"
Requires-Dist: sphinx-automodapi; extra == "docs"
Requires-Dist: sphinx-rtd-theme; extra == "docs"
Requires-Dist: stsci-rtd-theme; extra == "docs"
Requires-Dist: tomli; python_version < "3.11" and extra == "docs"
Dynamic: license-file
